Metadata-Version: 2.1
Name: Visual-Patterns
Version: 0.1.0
Summary: Programming practice exercises in pattern recognition, written in Python. Ideal for beginner programmers.
Home-page: https://github.com/asweigart/visualpatterns
Author: Al Sweigart
Author-email: al@inventwithpython.com
License: MIT
Platform: UNKNOWN
Classifier: License :: OSI Approved :: MIT License
Classifier: Programming Language :: Python
Classifier: Programming Language :: Python :: 3
Classifier: Programming Language :: Python :: 3.5
Classifier: Programming Language :: Python :: 3.6
Classifier: Programming Language :: Python :: 3.7
Classifier: Programming Language :: Python :: 3.8
Classifier: Programming Language :: Python :: 3.9
